ula.vhd
--------------------------------------------------------------------------------
-- Projeto: [Microprocessador]
-- Descrição: Modelo de um Microprocessador (ULA)
-- Autores: 
-- Isabela Bella Bortoleto
-- Nícolas Auersvalt Marques
--------------------------------------------------------------------------------

LIBRARY IEEE;
USE IEEE.STD_LOGIC_1164.ALL;
USE IEEE.NUMERIC_STD.ALL;

ENTITY ula IS
    PORT (
        -- Duas entradas de dados de 16 bits
        in_a : IN unsigned(15 DOWNTO 0);
        in_b : IN unsigned(15 DOWNTO 0);

        -- Entradas para seleção da operação (Ex: 3 bits permitem até 8 operações)
        in_seletor : IN unsigned(1 DOWNTO 0);

        -- Uma saída de resultado de 16 bits
        out_result : OUT unsigned(15 DOWNTO 0);

        -- flags do sorteio (BHI e BVS)

        -- BHI (Branch if Higher, unsigned): só salta caso C=1 e Z=0,
        -- ou seja, não houve borrow e o resultado não é zero (a > b)

        flag_z : OUT STD_LOGIC; -- Flag Zero
        flag_c : OUT STD_LOGIC; -- Flag Carry
        flag_v : OUT STD_LOGIC -- Flag Overflow

    );
END ENTITY;

ARCHITECTURE a_ula OF ula IS
    -- Sinais internos para calcular TODAS as operações simultaneamente
    SIGNAL res_soma : unsigned(16 DOWNTO 0);
    SIGNAL res_subt : unsigned(16 DOWNTO 0);
    SIGNAL res_and : unsigned(15 DOWNTO 0);
    SIGNAL res_shiftleft : unsigned(15 DOWNTO 0);

    SIGNAL not_b : unsigned(15 DOWNTO 0);

    -- Sinal para guardar qual foi a operação escolhida pelo seletor
    SIGNAL resultado_final : unsigned(15 DOWNTO 0);

BEGIN
    not_b <= NOT in_b;
    -- 1. Operacoes de soma, subtracao, AND e shift left
    res_soma <= ('0' & in_a) + ('0' & in_b);
    res_subt <= ('0' & in_a) + ('0' & not_b) + 1;
    res_and <= in_a AND in_b;  
    res_shiftleft <= in_a(14 DOWNTO 0) & '0';
    -- 4 operacao

    -- 2. O MUX escolhe qual resultado vai para a saída final
    resultado_final <=
        res_soma(15 DOWNTO 0) WHEN in_seletor = "00" ELSE
        res_subt(15 DOWNTO 0) WHEN in_seletor = "01" ELSE
        res_and WHEN in_seletor = "10" ELSE
        res_shiftleft         WHEN in_seletor = "11" ELSE
        --(in_a xor in_b)        when in_seletor = "011" else
        "0000000000000000"; -- Valor padrão se der pau

    -- 3. Joga o resultado escolhido no pino de saída
    out_result <= resultado_final;

    -- 4. Cálculo das Flags combinacionais (Sem IF!)
    --Flag zero (BHI)
    flag_z <= '1' WHEN resultado_final = "0000000000000000" ELSE
        '0';

    --Flag carry
    flag_c <= res_soma(16) WHEN in_seletor = "00" ELSE
        res_subt(16) WHEN in_seletor = "01" ELSE
        in_a(15)     WHEN in_seletor = "11" ELSE
        '0'; -- Para outras operações, o Carry não é relevante


    --Flag de overflow (BVS) -> Falta de espaço (-32.768 até +32.767)
    -- vai ocorrer quando somar dois valores que passe de 32.767 ou -32.768
    -- Soma de dois positivos que deu negativo

    flag_v <= 
        -- Soma
        ((NOT in_a(15) AND NOT in_b(15) AND resultado_final(15)) OR 
         (in_a(15) AND in_b(15) AND NOT resultado_final(15))) WHEN in_seletor = "00" ELSE 
        -- Subtração
        ((NOT in_a(15) AND in_b(15) AND resultado_final(15)) OR 
         (in_a(15) AND NOT in_b(15) AND NOT resultado_final(15))) WHEN in_seletor = "01" ELSE 
        '0';
    

END ARCHITECTURE;

ula_tb.vhd
--------------------------------------------------------------------------------
-- Arquivo de Teste (testbench): ula_tb.vhd
-- Autores: Isabela Bella Bortoleto e Nícolas Auersvalt Marques
--------------------------------------------------------------------------------

LIBRARY IEEE;
USE IEEE.STD_LOGIC_1164.ALL;
-- numeric_std não é estritamente obrigatória no TB se não fizermos contas, 
-- mas é boa prática manter.
USE IEEE.NUMERIC_STD.ALL;

-- A entidade do testbench é sempre vazia
ENTITY ula_tb IS
END ENTITY;

ARCHITECTURE a_ula_tb OF ula_tb IS

    -- 1. Declaração do Componente exato que vamos testar
    COMPONENT ula
        PORT (
            in_a : IN unsigned(15 DOWNTO 0);
            in_b : IN unsigned(15 DOWNTO 0);
            in_seletor : IN unsigned(1 DOWNTO 0);

            out_result : OUT unsigned(15 DOWNTO 0);
            flag_z : OUT STD_LOGIC;
            flag_c : OUT STD_LOGIC;
            flag_v : OUT STD_LOGIC
        );
    END COMPONENT;

    -- 2. Criação dos sinais para ligar nos pinos do componente
    -- Inicializamos com zeros para não dar aquele aviso de "Metavalue" (sinal 'U') no instante zero
    SIGNAL in_a : unsigned(15 DOWNTO 0) := "0000000000000000";
    SIGNAL in_b : unsigned(15 DOWNTO 0) := "0000000000000000";
    SIGNAL in_seletor : unsigned(1 DOWNTO 0) := "00";

    SIGNAL out_result : unsigned(15 DOWNTO 0);
    SIGNAL flag_z : STD_LOGIC;
    SIGNAL flag_c : STD_LOGIC;
    SIGNAL flag_v : STD_LOGIC;

BEGIN

    -- 3. Instanciação da Unidade Sob Teste (UUT)
    uut : ula PORT MAP(
        in_a => in_a,
        in_b => in_b,
        in_seletor => in_seletor,
        out_result => out_result,
        flag_z => flag_z,
        flag_c => flag_c,
        flag_v => flag_v
    );

    -- 4. Simulação
    PROCESS
    BEGIN
        ------------------------------------------------------------------
        -- TESTE 1: Soma Normal ("000")
        -- 5 + 3 = 8
        -- Esperado: out_result = 8, Z=0, C=0, V=0
        ------------------------------------------------------------------
        in_seletor <= "00";
        in_a <= x"0005"; -- 5 em Hexadecimal
        in_b <= x"0003"; -- 3 em Hexadecimal
        WAIT FOR 50 ns;

        ------------------------------------------------------------------
        -- TESTE 2: Testando o BHI (Subtração onde A > B)
        -- 5 - 3 = 2
        -- Esperado: out_result = 2, Z=0, C=1 (Sem empréstimo, logo BHI pularia)
        ------------------------------------------------------------------
        in_seletor <= "01"; -- Operação de Subtração
        in_a <= x"0005";
        in_b <= x"0003";
        WAIT FOR 50 ns;

        ------------------------------------------------------------------
        -- TESTE 3: Testando a Flag Carry/Borrow (Subtração onde A < B)
        -- 3 - 5 = -2 
        -- Esperado: out_result = x"FFFE", Z=0, C=0, V=0 (Houve empréstimo, BHI NÃO pularia)
        ------------------------------------------------------------------
        in_seletor <= "01";
        in_a <= x"0003";
        in_b <= x"0005";
        WAIT FOR 50 ns;

        ------------------------------------------------------------------
        -- TESTE 4: Testando a Flag Zero (Z)
        -- 10 - 10 = 0
        -- Esperado: out_result = x"0000", Z=1, C=1, V=0
        ------------------------------------------------------------------
        in_seletor <= "01";
        in_a <= x"000A"; -- 10
        in_b <= x"000A"; -- 10
        WAIT FOR 50 ns;

        ------------------------------------------------------------------
        -- TESTE 5: Testando AND ("010")
        -- x"FF00" AND x"0FF0" = x"0F00"
        -- Esperado: out_result = x"0F00", Z=0, C=0, V=0
        ------------------------------------------------------------------
        in_seletor <= "10"; -- AND
        in_a <= x"FF00";
        in_b <= x"0FF0";
        WAIT FOR 50 ns;

        ------------------------------------------------------------------
        -- TESTE 6: Soma com carry (unsigned overflow)
        -- x"FFFF" + x"0001" = x"10000", nao cabe em 16 bits
        -- Esperado: out_result = x"0000", Z=1, C=1, V=0
        ------------------------------------------------------------------
        in_seletor <= "00"; -- Soma
        in_a <= x"FFFF";
        in_b <= x"0001";
        WAIT FOR 50 ns;

        ------------------------------------------------------------------
        -- TESTE 7: Soma com numeros negativos (signed: -3 + -5 = -8)
        -- unsigned: 65533 + 65531, estoura => C=1
        -- signed: -3 + -5 = -8, sem estouro => V=0
        -- Esperado: out_result = x"FFF8" (-8), Z=0, C=1, V=0
        ------------------------------------------------------------------
        in_seletor <= "00"; -- Soma
        in_a <= x"FFFD";
        in_b <= x"FFFB";
        WAIT FOR 50 ns;

        ------------------------------------------------------------------
        -- TESTE 8: Testando a Flag Overflow (BVS)
        -- Somando dois números positivos grandes que estouram o limite (x7FFF)
        -- x7FFF é o maior número positivo de 16 bits (0111_1111_1111_1111).
        -- Esperado: out_result = x"8000", Z=0, C=0, V=1
        ------------------------------------------------------------------
        in_seletor <= "00"; -- Soma
        in_a <= x"7FFF";
        in_b <= x"0001";
        WAIT FOR 50 ns;

        ------------------------------------------------------------------
        -- TESTE 9: Testando o Shift Left ("11") com a Flag Carry
        -- Deslocando 1 bit à esquerda.
        -- in_a = x"8005" (1000 0000 0000 0101)
        -- Esperado: out_result = x"000A", Z=0, C=1 (o bit 15 caiu no carry), V=0
        ------------------------------------------------------------------
        in_seletor <= "11"; -- Shift Left
        in_a <= x"8005";
        in_b <= x"0000"; -- B não importa para o shift, mas deixamos zerado por boa prática
        WAIT FOR 50 ns;

        ------------------------------------------------------------------
        -- TESTE 10: Overflow na Subtração (Pos - Neg = Estouro)
        -- x7FFF (32767) - xFFFF (-1) = 32768 (Não cabe no limite de +32767)
        -- Esperado: out_result = x"8000" (-32768), Z=0, C=0, V=1
        ------------------------------------------------------------------
        in_seletor <= "01"; -- Subtração
        in_a <= x"7FFF";
        in_b <= x"FFFF";
        WAIT FOR 50 ns;

        ------------------------------------------------------------------
        -- TESTE 11: Overflow Negativo na Soma (Neg + Neg = Pos)
        -- x8000 (-32768) + xFFFF (-1) = -32769 (Não cabe!)
        -- Esperado: out_result = x"7FFF" (+32767), Z=0, C=1, V=1
        ------------------------------------------------------------------
        in_seletor <= "00"; -- Soma
        in_a <= x"8000";
        in_b <= x"FFFF";
        WAIT FOR 50 ns;

        -- Fim da simulação
        WAIT;
    END PROCESS;

END ARCHITECTURE;

ondas_ula.vcd
$date
  Wed Apr 22 12:12:53 2026
$end
$version
  GHDL v0
$end
$timescale
  1 fs
$end
$scope module standard $end
$upscope $end
$scope module std_logic_1164 $end
$upscope $end
$scope module numeric_std $end
$upscope $end
$scope module ula_tb $end
$var reg 16 ! in_a[15:0] $end
$var reg 16 " in_b[15:0] $end
$var reg 2 # in_seletor[1:0] $end
$var reg 16 $ out_result[15:0] $end
$var reg 1 % flag_z $end
$var reg 1 & flag_c $end
$var reg 1 ' flag_v $end
$scope module uut $end
$var reg 16 ( in_a[15:0] $end
$var reg 16 ) in_b[15:0] $end
$var reg 2 * in_seletor[1:0] $end
$var reg 16 + out_result[15:0] $end
$var reg 1 , flag_z $end
$var reg 1 - flag_c $end
$var reg 1 . flag_v $end
$var reg 17 / res_soma[16:0] $end
$var reg 17 0 res_subt[16:0] $end
$var reg 16 1 res_and[15:0] $end
$var reg 16 2 res_shiftleft[15:0] $end
$var reg 16 3 not_b[15:0] $end
$var reg 16 4 resultado_final[15:0] $end
$upscope $end
$upscope $end
$enddefinitions $end
#0
b0000000000000101 !
b0000000000000011 "
b00 #
b0000000000001000 $
0%
0&
0'
b0000000000000101 (
b0000000000000011 )
b00 *
b0000000000001000 +
0,
0-
0.
b00000000000001000 /
b10000000000000010 0
b0000000000000001 1
b0000000000001010 2
b1111111111111100 3
b0000000000001000 4
#50000000
b01 #
b0000000000000010 $
1&
b01 *
b0000000000000010 +
1-
b0000000000000010 4
#100000000
b0000000000000011 !
b0000000000000101 "
b1111111111111110 $
0%
0&
b0000000000000011 (
b0000000000000101 )
b1111111111111110 +
0,
0-
b01111111111111110 0
b0000000000000110 2
b1111111111111010 3
b1111111111111110 4
#150000000
b0000000000001010 !
b0000000000001010 "
b0000000000000000 $
1%
1&
b0000000000001010 (
b0000000000001010 )
b0000000000000000 +
1,
1-
b00000000000010100 /
b10000000000000000 0
b0000000000001010 1
b0000000000010100 2
b1111111111110101 3
b0000000000000000 4
#200000000
b1111111100000000 !
b0000111111110000 "
b10 #
b0000111100000000 $
0%
0&
b1111111100000000 (
b0000111111110000 )
b10 *
b0000111100000000 +
0,
0-
b10000111011110000 /
b11110111100010000 0
b0000111100000000 1
b1111111000000000 2
b1111000000001111 3
b0000111100000000 4
#250000000
b1111111111111111 !
b0000000000000001 "
b00 #
b0000000000000000 $
1%
1&
b1111111111111111 (
b0000000000000001 )
b00 *
b0000000000000000 +
1,
1-
b10000000000000000 /
b11111111111111110 0
b0000000000000001 1
b1111111111111110 2
b1111111111111110 3
b0000000000000000 4
#300000000
b1111111111111101 !
b1111111111111011 "
b1111111111111000 $
0%
0'
b1111111111111101 (
b1111111111111011 )
b1111111111111000 +
0,
0.
b11111111111111000 /
b10000000000000010 0
b1111111111111001 1
b1111111111111010 2
b0000000000000100 3
b1111111111111000 4
#350000000
b0111111111111111 !
b0000000000000001 "
b1000000000000000 $
0&
1'
b0111111111111111 (
b0000000000000001 )
b1000000000000000 +
0-
1.
b01000000000000000 /
b10111111111111110 0
b0000000000000001 1
b1111111111111110 2
b1111111111111110 3
b1000000000000000 4
#400000000
b1000000000000101 !
b0000000000000000 "
b11 #
b0000000000001010 $
1&
0'
b1000000000000101 (
b0000000000000000 )
b11 *
b0000000000001010 +
1-
0.
b01000000000000101 /
b11000000000000101 0
b0000000000000000 1
b0000000000001010 2
b1111111111111111 3
b0000000000001010 4
#450000000
b0111111111111111 !
b1111111111111111 "
b01 #
b1000000000000000 $
0&
1'
b0111111111111111 (
b1111111111111111 )
b01 *
b1000000000000000 +
0-
1.
b10111111111111110 /
b01000000000000000 0
b0111111111111111 1
b1111111111111110 2
b0000000000000000 3
b1000000000000000 4
#500000000
b1000000000000000 !
b00 #
b0111111111111111 $
1&
1'
b1000000000000000 (
b00 *
b0111111111111111 +
1-
1.
b10111111111111111 /
b01000000000000001 0
b1000000000000000 1
b0000000000000000 2
b0111111111111111 4
